pybgpasn/__init__.py
pybgpasn/bgp_asn_db.py
pybgpasn/pybgpasn.py
pybgpasn-1.0.13.dist-info/LICENSE
pybgpasn-1.0.13.dist-info/METADATA
pybgpasn-1.0.13.dist-info/WHEEL
pybgpasn-1.0.13.dist-info/RECORD
